<?xml version="1.0" encoding="UTF-8"?>
<objects serializationModel="Studio.02.03.00">
	<object class="AudioFile" id="{121ffe18-4e6d-45e1-9d67-0d610d6dca95}">
		<property name="assetPath">
			<value>UI/SFX_LilaCallOut.wav</value>
		</property>
		<property name="frequencyInKHz">
			<value>48</value>
		</property>
		<property name="channelCount">
			<value>2</value>
		</property>
		<property name="length">
			<value>0.59339583333333334</value>
		</property>
		<relationship name="masterAssetFolder">
			<destination>{681caa4e-8d56-41dc-843e-3ed544368314}</destination>
		</relationship>
	</object>
</objects>
